pmct/__init__.py
pmct/core.py
pmct/tests.py
pmct-1.0.0.dist-info/licenses/LICENSE
pmct-1.0.0.dist-info/METADATA
pmct-1.0.0.dist-info/WHEEL
pmct-1.0.0.dist-info/top_level.txt
pmct-1.0.0.dist-info/RECORD
