Metadata-Version: 2.4
Name: pmct
Version: 1.0.0
Summary: Python Module for Cointegration Tests with Two Endogenous Structural Breaks
Home-page: https://github.com/merwanroudane/pmct
Author: Dr. Merwan Roudane
Author-email: "Dr. Merwan Roudane" <merwanroudane920@gmail.com>
Maintainer-email: "Dr. Merwan Roudane" <merwanroudane920@gmail.com>
License: GPL-3.0
Project-URL: Homepage, https://github.com/merwanroudane/pmct
Project-URL: Documentation, https://github.com/merwanroudane/pmct#readme
Project-URL: Repository, https://github.com/merwanroudane/pmct
Project-URL: Bug Tracker, https://github.com/merwanroudane/pmct/issues
Project-URL: Changelog, https://github.com/merwanroudane/pmct/blob/main/CHANGELOG.md
Keywords: cointegration,econometrics,time-series,structural-breaks,unit-root
Classifier: Development Status :: 4 - Beta
Classifier: Intended Audience :: Science/Research
Classifier: Intended Audience :: Financial and Insurance Industry
Classifier: Topic :: Scientific/Engineering
Classifier: Topic :: Scientific/Engineering :: Mathematics
Classifier: License :: OSI Approved :: GNU General Public License v3 (GPLv3)
Classifier: Programming Language :: Python :: 3
Classifier: Programming Language :: Python :: 3.7
Classifier: Programming Language :: Python :: 3.8
Classifier: Programming Language :: Python :: 3.9
Classifier: Programming Language :: Python :: 3.10
Classifier: Programming Language :: Python :: 3.11
Classifier: Programming Language :: Python :: 3.12
Classifier: Operating System :: OS Independent
Requires-Python: >=3.7
License-File: LICENSE
Requires-Dist: numpy>=1.19.0
Requires-Dist: pandas>=1.1.0
Provides-Extra: dev
Requires-Dist: pytest>=6.0; extra == "dev"
Requires-Dist: pytest-cov>=2.10; extra == "dev"
Requires-Dist: sphinx>=3.0; extra == "dev"
Requires-Dist: black>=20.0; extra == "dev"
Requires-Dist: flake8>=3.8; extra == "dev"
Requires-Dist: mypy>=0.800; extra == "dev"
Dynamic: author
Dynamic: home-page
Dynamic: license-file
Dynamic: requires-python
